ossr_utils/__init__.py
ossr_utils/audio_utils.py
ossr_utils/fft_utils.py
ossr_utils/io_utils.py
ossr_utils/misc_utils.py
ossr_utils/model_utils.py
ossr_utils-0.1.6.dist-info/METADATA
ossr_utils-0.1.6.dist-info/WHEEL
ossr_utils-0.1.6.dist-info/RECORD
