Metadata-Version: 2.1
Name: ossr-utils
Version: 0.1.6
Summary: Utils for the Open-Set Sound Recognition (OSSR) system
License: MIT
Author: Johannes Traa
Requires-Python: >=3.8,<4.0
Classifier: License :: OSI Approved :: MIT License
Classifier: Programming Language :: Python :: 3
Classifier: Programming Language :: Python :: 3.8
Classifier: Programming Language :: Python :: 3.9
Classifier: Programming Language :: Python :: 3.10
Classifier: Programming Language :: Python :: 3.11
Requires-Dist: matplotlib (>=3.7.1,<4.0.0)
Requires-Dist: pandas (>=2.0.1,<3.0.0)
